tomeks_torrent_manager/__init__.py
tomeks_torrent_manager/torrent_manager.py
tomeks_torrent_manager/pull_torrent_info/__init__.py
tomeks_torrent_manager/pull_torrent_info/database.py
tomeks_torrent_manager/pull_torrent_info/source_rss.py
tomeks_torrent_manager/pull_torrent_info/source_transmission.py
tomeks_torrent_manager/pull_torrent_info/source_website.py
tomeks_torrent_manager/pull_torrent_info/utils.py
tomeks_torrent_manager-0.0.11.dist-info/METADATA
tomeks_torrent_manager-0.0.11.dist-info/WHEEL
tomeks_torrent_manager-0.0.11.dist-info/licenses/LICENSE
tomeks_torrent_manager-0.0.11.dist-info/RECORD
