Metadata-Version: 2.1
Name: tomeks_torrent_manager
Version: 0.0.11
Summary: My torrent manager
Project-URL: Homepage, https://github.com/pypa/sampleproject
Project-URL: Bug Tracker, https://github.com/pypa/sampleproject/issues
Author-email: Tomek <thomas.r.waller@gmail.com>
License-File: LICENSE
Classifier: License :: OSI Approved :: MIT License
Classifier: Operating System :: OS Independent
Classifier: Programming Language :: Python :: 3
Requires-Python: >=3.10
Requires-Dist: beautifulsoup4==4.10.0
Requires-Dist: datasize==1.0.0
Requires-Dist: feedparser==6.0.10
Requires-Dist: pytimeparse==1.1.8
Requires-Dist: requests==2.28.1
Requires-Dist: tqdm
Requires-Dist: transmission-clutch==6.0.3
